LICENSE
MANIFEST.in
README.rst
VERSION
requirements.txt
setup.cfg
setup.py
src/pytest_appengine/__init__.py
src/pytest_appengine/fixtures.py
src/pytest_appengine/plugin.py
src/pytest_appengine.egg-info/PKG-INFO
src/pytest_appengine.egg-info/SOURCES.txt
src/pytest_appengine.egg-info/dependency_links.txt
src/pytest_appengine.egg-info/entry_points.txt
src/pytest_appengine.egg-info/top_level.txt