Metadata-Version: 1.1
Name: pytest-appengine
Version: 0.0.2
Summary: AppEngine integration that works well with pytest-django
Home-page: https://github.com/novopl/pytest-appengine
Author: Mateusz 'novo' Klos
Author-email: novopl@gmail.com
License: MIT
Platform: UNKNOWN
Classifier: Framework :: Pytest
Classifier: Topic :: Software Development :: Testing
Classifier: Intended Audience :: Developers
Classifier: Programming Language :: Python
Classifier: Programming Language :: Python :: 2.7
Classifier: Programming Language :: Python :: 3.3
Classifier: Programming Language :: Python :: 3.4
Classifier: Programming Language :: Python :: 3.5
Classifier: Programming Language :: Python :: 3.6
Classifier: License :: OSI Approved :: MIT License
